papermc_api/__init__.py
papermc_api/api_client.py
papermc_api/api_response.py
papermc_api/configuration.py
papermc_api/exceptions.py
papermc_api/py.typed
papermc_api/rest.py
papermc_api/api/__init__.py
papermc_api/api/download_controller_api.py
papermc_api/api/project_controller_api.py
papermc_api/api/projects_controller_api.py
papermc_api/api/version_build_controller_api.py
papermc_api/api/version_builds_controller_api.py
papermc_api/api/version_controller_api.py
papermc_api/api/version_family_builds_controller_api.py
papermc_api/api/version_family_controller_api.py
papermc_api/models/__init__.py
papermc_api/models/build_response.py
papermc_api/models/builds_response.py
papermc_api/models/change.py
papermc_api/models/download.py
papermc_api/models/project_response.py
papermc_api/models/projects_response.py
papermc_api/models/version_build.py
papermc_api/models/version_family_build.py
papermc_api/models/version_family_builds_response.py
papermc_api/models/version_family_response.py
papermc_api/models/version_response.py
papermc_api-2024.3.dist-info/METADATA
papermc_api-2024.3.dist-info/WHEEL
papermc_api-2024.3.dist-info/top_level.txt
papermc_api-2024.3.dist-info/RECORD
