Metadata-Version: 2.1
Name: papermc-api
Version: 2024.3
Summary: PaperMC API
Home-page: 
Author: OpenAPI Generator community
Author-email: team@openapitools.org
Keywords: OpenAPI,OpenAPI-Generator,PaperMC API
Requires-Dist: urllib3 <2.1.0,>=1.25.3
Requires-Dist: python-dateutil
Requires-Dist: pydantic >=2
Requires-Dist: typing-extensions >=4.7.1
